clearcache/__init__.py
clearcache/apps.py
clearcache/forms.py
clearcache/management/__init__.py
clearcache/management/commands/__init__.py
clearcache/management/commands/clearcache.py
clearcache/templates/admin/index.html
clearcache/templates/clearcache/admin/clearcache_form.html
clearcache/tests.py
clearcache/urls.py
clearcache/utils.py
clearcache/views.py
django_clearcache_backport-1.0.0.dist-info/LICENSE
django_clearcache_backport-1.0.0.dist-info/WHEEL
django_clearcache_backport-1.0.0.dist-info/METADATA
django_clearcache_backport-1.0.0.dist-info/RECORD
