Metadata-Version: 2.1
Name: django-clearcache-backport
Version: 1.0.0
Summary: Allows you to clear Django cache via admin UI or manage.py command
Home-page: https://github.com/bernardoduarte
License: MIT
Keywords: django,cache
Author: Bernardo Duarte
Author-email: bernardoeiraduarte@gmail.com
Requires-Python: >=2.7,<3.0
Classifier: Development Status :: 5 - Production/Stable
Classifier: Environment :: Web Environment
Classifier: Framework :: Django
Classifier: Framework :: Django :: 1.10
Classifier: Framework :: Django :: 1.11
Classifier: Intended Audience :: Developers
Classifier: License :: OSI Approved :: MIT License
Classifier: Operating System :: OS Independent
Classifier: Programming Language :: Python :: 2
Classifier: Programming Language :: Python :: 2.7
Classifier: Topic :: Software Development :: Libraries
Classifier: Topic :: Utilities
Requires-Dist: django (>=1.10.0,<2.0.0)
Project-URL: Repository, https://github.com/bernardoduarte/django-clearcache-backport
